dual_quaternions_ros/__init__.py
dual_quaternions_ros/dual_quaternions_ros.py
dual_quaternions_ros-0.1.0.dist-info/LICENSE
dual_quaternions_ros-0.1.0.dist-info/METADATA
dual_quaternions_ros-0.1.0.dist-info/WHEEL
dual_quaternions_ros-0.1.0.dist-info/top_level.txt
dual_quaternions_ros-0.1.0.dist-info/RECORD
