Metadata-Version: 2.1
Name: dual-quaternions-ros
Version: 0.1.0
Summary: Dual quaternion ROS converter
Home-page: http://github.com/Achllle/dual_quaternions_ros/tree/master/dual_quaternions_ros
Author: Achille Verheye
Author-email: achille.verheye@gmail.com
License: MIT
Platform: UNKNOWN
Requires-Dist: dual-quaternions
